aiotinyrpc/__init__.py
aiotinyrpc/auth.py
aiotinyrpc/client.py
aiotinyrpc/dispatch/__init__.py
aiotinyrpc/exc.py
aiotinyrpc/log.py
aiotinyrpc/protocols/__init__.py
aiotinyrpc/protocols/jsonrpc.py
aiotinyrpc/protocols/msgpackrpc.py
aiotinyrpc/server/__init__.py
aiotinyrpc/server/gevent.py
aiotinyrpc/transports/__init__.py
aiotinyrpc/transports/callback.py
aiotinyrpc/transports/cgi.py
aiotinyrpc/transports/http.py
aiotinyrpc/transports/rabbitmq.py
aiotinyrpc/transports/socket.py
aiotinyrpc/transports/socketmessages.py
aiotinyrpc/transports/websocket.py
aiotinyrpc/transports/websocketclient.py
aiotinyrpc/transports/wsgi.py
aiotinyrpc/transports/zmq.py
aiotinyrpc-0.8.3.dist-info/LICENSE
aiotinyrpc-0.8.3.dist-info/WHEEL
aiotinyrpc-0.8.3.dist-info/METADATA
aiotinyrpc-0.8.3.dist-info/RECORD
