Metadata-Version: 2.1
Name: aiotinyrpc
Version: 0.8.3
Summary: "An aio version of tinyrpc"
License: MIT
Author: David White
Author-email: dr.white.nz@gmail.com
Requires-Python: >=3.8,<4.0
Classifier: License :: OSI Approved :: MIT License
Classifier: Programming Language :: Python :: 3
Classifier: Programming Language :: Python :: 3.8
Classifier: Programming Language :: Python :: 3.9
Classifier: Programming Language :: Python :: 3.10
Classifier: Programming Language :: Python :: 3.11
Provides-Extra: gevent
Provides-Extra: httpclient
Provides-Extra: jsonext
Provides-Extra: msgpack
Provides-Extra: rabbitmq
Provides-Extra: socket
Provides-Extra: websocket
Provides-Extra: wsgi
Provides-Extra: zmq
Requires-Dist: gevent (>=21.1.2,<22.0.0); extra == "gevent"
Requires-Dist: gevent-websocket (>=0.10.1,<0.11.0); extra == "httpclient" or extra == "websocket"
Requires-Dist: msgpack (>=1.0.2,<2.0.0); extra == "msgpack"
Requires-Dist: pika (>=1.2.0,<2.0.0); extra == "rabbitmq"
Requires-Dist: pycryptodomex (>=3.15.0,<4.0.0); extra == "socket"
Requires-Dist: pymongo (>=4.3.2,<5.0.0); extra == "socket"
Requires-Dist: python-bitcoinlib (>=0.11.2,<0.12.0); extra == "socket"
Requires-Dist: pyzmq (>=22.0.3,<23.0.0); extra == "zmq"
Requires-Dist: requests (>=2.28.1,<3.0.0); extra == "httpclient"
Requires-Dist: six (>=1.16.0,<2.0.0)
Requires-Dist: werkzeug (>=2.2.2,<3.0.0); extra == "wsgi"
